{"books":[{"name":"ଏପିସିୟ","chapters":6},{"name":"ଏବ୍ରି","chapters":13},{"name":"କଲସିୟ","chapters":4},{"name":"ଗାଲାତିୟ","chapters":6},{"name":"ଜହନ୍‌","chapters":21},{"name":"ଜାକ୍‌ବ","chapters":5},{"name":"ଜିହୁଦା","chapters":1},{"name":"ପକ୍ୟାତାକା","chapters":28},{"name":"ପିଲିପିୟ","chapters":4},{"name":"ପିଲିମନ୍‌","chapters":1},{"name":"ମାତିଉ","chapters":28},{"name":"ମାର୍କ","chapters":16},{"name":"ରମିୟ","chapters":16},{"name":"ଲୁକ","chapters":24},{"name":"ହତ୍‌ତି","chapters":22},{"name":"୧କରନ୍ତିୟ","chapters":16},{"name":"୧ଜହନ୍‌","chapters":5},{"name":"୧ତିମତି","chapters":6},{"name":"୧ତେସ୍‌ଲନିକି","chapters":5},{"name":"୧ପିତର୍‌ତି","chapters":5},{"name":"୨କରନ୍ତିୟ","chapters":13},{"name":"୨ଜହନ୍‌","chapters":1},{"name":"୨ତେସ୍‌ଲନିକି","chapters":3},{"name":"୨ପିତର୍‌ତି","chapters":3},{"name":"୩ଜହନ୍‌","chapters":1}]}