{"books":[{"name":"1cácvua","chapters":22},{"name":"1cô-rinh-tô","chapters":16},{"name":"1giăng","chapters":5},{"name":"1phi-e-rơ","chapters":5},{"name":"1sa-mu-ên","chapters":31},{"name":"1sửký","chapters":29},{"name":"1ti-mô-thê","chapters":6},{"name":"1tê-sa-lô-ni-ca","chapters":5},{"name":"2cácvua","chapters":25},{"name":"2cô-rinh-tô","chapters":13},{"name":"2giăng","chapters":1},{"name":"2phi-e-rơ","chapters":3},{"name":"2sa-mu-ên","chapters":24},{"name":"2sửký","chapters":36},{"name":"2ti-mô-thê","chapters":4},{"name":"2tê-sa-lô-ni-ca","chapters":3},{"name":"3giăng","chapters":1},{"name":"a-gai","chapters":2},{"name":"a-mốt","chapters":9},{"name":"aica","chapters":5},{"name":"châmngôn","chapters":31},{"name":"cô-lô-se","chapters":4},{"name":"côngvụcácsứđồ","chapters":28},{"name":"dânsốký","chapters":36},{"name":"e-xơ-ra","chapters":10},{"name":"ga-la-ti","chapters":6},{"name":"gia-cơ","chapters":5},{"name":"giu-đe","chapters":1},{"name":"giê-rê-mi","chapters":52},{"name":"gióp","chapters":42},{"name":"giô-na","chapters":4},{"name":"giô-suê","chapters":24},{"name":"giô-ên","chapters":3},{"name":"giăng","chapters":21},{"name":"ha-ba-cúc","chapters":3},{"name":"hê-bơ-rơ","chapters":13},{"name":"khảihuyền","chapters":22},{"name":"lu-ca","chapters":24},{"name":"lê-viký","chapters":27},{"name":"ma-la-chi","chapters":4},{"name":"ma-thi-ơ","chapters":28},{"name":"mi-ca","chapters":7},{"name":"mác","chapters":16},{"name":"na-hum","chapters":3},{"name":"nhãca","chapters":8},{"name":"nê-hê-mi","chapters":13},{"name":"phi-lê-môn","chapters":1},{"name":"phi-líp","chapters":4},{"name":"phụctruyềnluậtlệký","chapters":34},{"name":"ru-tơ","chapters":4},{"name":"rô-ma","chapters":16},{"name":"sángthếký","chapters":50},{"name":"sô-phô-ni","chapters":3},{"name":"thithiên","chapters":150},{"name":"thẩmphán","chapters":21},{"name":"truyềnđạo","chapters":12},{"name":"tích","chapters":3},{"name":"xa-cha-ri","chapters":14},{"name":"xuấtaicập","chapters":40},{"name":"y-sai","chapters":66},{"name":"áp-đia","chapters":1},{"name":"ê-phê-sô","chapters":6},{"name":"ê-xê-chi-ên","chapters":48},{"name":"ê-xơ-tê","chapters":10},{"name":"ô-sê","chapters":14},{"name":"đa-ni-ên","chapters":12}]}