{"books":[{"name":"אגרתוהראשונהשליוחנןהשליח","chapters":5},{"name":"אגרתוהראשונהשלפטרוסהשליח","chapters":5},{"name":"אגרתוהשלישיתשליוחנןהשליח","chapters":1},{"name":"אגרתוהשנייהשליוחנןהשליח","chapters":1},{"name":"אגרתוהשנייהשלפטרוסהשליח","chapters":3},{"name":"אגרתיהודה","chapters":1},{"name":"אגרתיעקב","chapters":5},{"name":"אגרתפולוסאל-טיטוס","chapters":3},{"name":"אגרתפולוסאל-פילימון","chapters":1},{"name":"אגרתפולוסהראשונהאל-הקורנתים","chapters":16},{"name":"אגרתפולוסהראשונהאל-התסלוניקים","chapters":5},{"name":"אגרתפולוסהראשונהאל-טימותיוס","chapters":6},{"name":"אגרתפולוסהשליחאל-הגלטים","chapters":6},{"name":"אגרתפולוסהשליחאל-הפיליפיים","chapters":4},{"name":"אגרתפולוסהשליחאל-הקולוסים","chapters":4},{"name":"אגרתפולוסהשליחאל-הרומיים","chapters":16},{"name":"אגרתפולוסהשליחאלהאפסיים","chapters":6},{"name":"אגרתפולוסהשנייהאל-הקורנתים","chapters":13},{"name":"אגרתפולוסהשנייהאל-התסלוניקים","chapters":3},{"name":"אגרתפולוסהשנייהאל-טימותיוס","chapters":4},{"name":"האיגרתאל-העברים","chapters":13},{"name":"הבשורהעל-פייוחנן","chapters":21},{"name":"הבשורהעל-פילוקס","chapters":24},{"name":"הבשורהעל-פימרקוס","chapters":16},{"name":"הבשורהעל-פימתי","chapters":28},{"name":"התגלות","chapters":22},{"name":"מעשיהשליחים","chapters":28}]}