{"books":[{"name":"1bhakolinto","chapters":16},{"name":"1bhateshalonike","chapters":5},{"name":"1petili","chapters":5},{"name":"1timoteo","chapters":6},{"name":"1yowana","chapters":5},{"name":"2bhakolinto","chapters":13},{"name":"2bhateshalonike","chapters":3},{"name":"2petili","chapters":3},{"name":"2timoteo","chapters":4},{"name":"2yowana","chapters":1},{"name":"3yowana","chapters":1},{"name":"bhaebhulania","chapters":13},{"name":"bhaepheso","chapters":6},{"name":"bhagalatia","chapters":6},{"name":"bhakoloshai","chapters":4},{"name":"bhalumi","chapters":16},{"name":"bhapilipi","chapters":4},{"name":"itendi","chapters":28},{"name":"luka","chapters":24},{"name":"maliko","chapters":16},{"name":"matei","chapters":28},{"name":"maunukulo","chapters":22},{"name":"pilimoni","chapters":1},{"name":"tito","chapters":3},{"name":"yakobho","chapters":5},{"name":"yowana","chapters":21},{"name":"yuda","chapters":1}]}